autopkg_wrapper/__init__.py
autopkg_wrapper/autopkg_wrapper.py
autopkg_wrapper/notifier/__init__.py
autopkg_wrapper/notifier/slack.py
autopkg_wrapper/utils/__init__.py
autopkg_wrapper/utils/args.py
autopkg_wrapper/utils/git_functions.py
autopkg_wrapper/utils/logging.py
autopkg_wrapper-2025.8.1.dist-info/METADATA
autopkg_wrapper-2025.8.1.dist-info/WHEEL
autopkg_wrapper-2025.8.1.dist-info/entry_points.txt
autopkg_wrapper-2025.8.1.dist-info/licenses/LICENSE
autopkg_wrapper-2025.8.1.dist-info/RECORD
