Metadata-Version: 2.4
Name: autopkg-wrapper
Version: 2025.8.1
Summary: A package used to execute some autopkg functions, primarily within the context of a GitHub Actions runner.
Project-URL: Repository, https://github.com/smithjw/autopkg-wrapper
Author-email: James Smith <james@smithjw.me>
License-Expression: BSD-3-Clause
License-File: LICENSE
Requires-Python: ~=3.12.0
Requires-Dist: chardet
Requires-Dist: idna
Requires-Dist: pygithub
Requires-Dist: requests
Requires-Dist: ruamel-yaml
Requires-Dist: toml
Requires-Dist: urllib3
